[{
    "permission": {
        "0": "Title#RaqStar",
        "1": "Desc#Reader of Raw Star",
        "3": "Tytpe#Entertainment",
        "4": "Rating#4.5"
    },
    "id": "233",
    "name": "Movie Raw Star"
}, {
    "permission": {
        "0": "Title#RaqStar",
        "3": "Tytpe#Entertainment",
        "4": "Rating#4.5"
    },
    "id": "233",
    "name": "Movie Raw Star"
}, {
    "permission": {
        "1": "Desc#Reader of Raw Star",
        "3": "Tytpe#Entertainment",
        "4": "Rating#4.5"
    },
    "id": "233",
    "name": "Movie Raw Star"
}, {
    "permission": {
        "1": "Desc#Reader of Raw Star",
        "4": "Rating#4.5"
    },
    "id": "233",
    "name": "Movie Raw Star"
}]